{
  "updated": "2026-05-23T03:55:27.580Z",
  "region": "na",
  "prices": {
    "adv_spare": {
      "id": "y3nmw",
      "avg24h": 69078,
      "mean24h": 63940,
      "median24h": 64900,
      "sampleCountLast24h": 86,
      "cleanSampleCount24h": 83,
      "outliersRemoved24h": 3,
      "min24h": 45000,
      "max24h": 75000,
      "avg7d": 68015,
      "mean7d": 65059,
      "median7d": 65000,
      "sampleCountLast7d": 690,
      "cleanSampleCount7d": 648,
      "outliersRemoved7d": 42,
      "min7d": 47500,
      "max7d": 83333,
      "totalUnits7d": 13491
    },
    "std_spare": {
      "id": "l0og1",
      "avg24h": 23459,
      "mean24h": 27806,
      "median24h": 22222,
      "sampleCountLast24h": 39,
      "cleanSampleCount24h": 35,
      "outliersRemoved24h": 4,
      "min24h": 18000,
      "max24h": 41667,
      "avg7d": 22397,
      "mean7d": 23416,
      "median7d": 22222,
      "sampleCountLast7d": 263,
      "cleanSampleCount7d": 224,
      "outliersRemoved7d": 39,
      "min7d": 10000,
      "max7d": 38988,
      "totalUnits7d": 4572
    },
    "cheap_spare": {
      "id": "j0w96",
      "avg24h": null,
      "mean24h": null,
      "median24h": null,
      "sampleCountLast24h": 0,
      "cleanSampleCount24h": 0,
      "min24h": null,
      "max24h": null,
      "avg7d": 11883,
      "mean7d": 15533,
      "median7d": 14000,
      "sampleCountLast7d": 9,
      "cleanSampleCount7d": 9,
      "outliersRemoved7d": 0,
      "min7d": 10000,
      "max7d": 25000,
      "totalUnits7d": 120
    },
    "adv_tool": {
      "id": "4q7pl",
      "avg24h": 68529,
      "mean24h": 63097,
      "median24h": 63789,
      "sampleCountLast24h": 116,
      "cleanSampleCount24h": 114,
      "outliersRemoved24h": 2,
      "min24h": 45000,
      "max24h": 80000,
      "avg7d": 70645,
      "mean7d": 65734,
      "median7d": 65000,
      "sampleCountLast7d": 689,
      "cleanSampleCount7d": 648,
      "outliersRemoved7d": 41,
      "min7d": 46667,
      "max7d": 82000,
      "totalUnits7d": 9045
    },
    "std_tool": {
      "id": "qjqw9",
      "avg24h": 18522,
      "mean24h": 19103,
      "median24h": 19700,
      "sampleCountLast24h": 40,
      "cleanSampleCount24h": 27,
      "outliersRemoved24h": 13,
      "min24h": 16250,
      "max24h": 21010,
      "avg7d": 15388,
      "mean7d": 17798,
      "median7d": 18000,
      "sampleCountLast7d": 325,
      "cleanSampleCount7d": 298,
      "outliersRemoved7d": 27,
      "min7d": 8000,
      "max7d": 30000,
      "totalUnits7d": 7216
    },
    "cheap_tool": {
      "id": "wjlrd",
      "avg24h": null,
      "mean24h": null,
      "median24h": null,
      "sampleCountLast24h": 0,
      "cleanSampleCount24h": 0,
      "min24h": null,
      "max24h": null,
      "avg7d": 25000,
      "mean7d": 39583,
      "median7d": 50000,
      "sampleCountLast7d": 3,
      "cleanSampleCount7d": 3,
      "outliersRemoved7d": 0,
      "min7d": 18750,
      "max7d": 50000,
      "totalUnits7d": 10
    },
    "str_boar": {
      "id": "5lo3o",
      "avg24h": 7387,
      "mean24h": 7373,
      "median24h": 7143,
      "sampleCountLast24h": 68,
      "cleanSampleCount24h": 67,
      "outliersRemoved24h": 1,
      "min24h": 6000,
      "max24h": 8254,
      "avg7d": 7302,
      "mean7d": 7302,
      "median7d": 7143,
      "sampleCountLast7d": 340,
      "cleanSampleCount7d": 299,
      "outliersRemoved7d": 41,
      "min7d": 4929,
      "max7d": 9524,
      "totalUnits7d": 2082
    },
    "polymer": {
      "id": "jl26",
      "avg24h": 3322,
      "mean24h": 3321,
      "median24h": 3200,
      "sampleCountLast24h": 8,
      "cleanSampleCount24h": 8,
      "outliersRemoved24h": 0,
      "min24h": 3125,
      "max24h": 4246,
      "avg7d": 3922,
      "mean7d": 3921,
      "median7d": 4000,
      "sampleCountLast7d": 55,
      "cleanSampleCount7d": 50,
      "outliersRemoved7d": 5,
      "min7d": 3022,
      "max7d": 5400,
      "totalUnits7d": 2498
    },
    "water_carrier": {
      "id": "m22k",
      "avg24h": 611,
      "mean24h": 611,
      "median24h": 640,
      "sampleCountLast24h": 28,
      "cleanSampleCount24h": 28,
      "outliersRemoved24h": 0,
      "min24h": 380,
      "max24h": 1200,
      "avg7d": 883,
      "mean7d": 883,
      "median7d": 920,
      "sampleCountLast7d": 141,
      "cleanSampleCount7d": 132,
      "outliersRemoved7d": 9,
      "min7d": 360,
      "max7d": 1600,
      "totalUnits7d": 6576
    },
    "plastic_bottle": {
      "id": "pry2",
      "avg24h": 3330,
      "mean24h": 3330,
      "median24h": 3499,
      "sampleCountLast24h": 53,
      "cleanSampleCount24h": 42,
      "outliersRemoved24h": 11,
      "min24h": 3000,
      "max24h": 3499,
      "avg7d": 2421,
      "mean7d": 2416,
      "median7d": 2500,
      "sampleCountLast7d": 213,
      "cleanSampleCount7d": 212,
      "outliersRemoved7d": 1,
      "min7d": 1000,
      "max7d": 4000,
      "totalUnits7d": 2098
    },
    "ammonia": {
      "id": "40vn",
      "avg24h": 17925,
      "mean24h": 18019,
      "median24h": 18000,
      "sampleCountLast24h": 44,
      "cleanSampleCount24h": 43,
      "outliersRemoved24h": 1,
      "min24h": 13043,
      "max24h": 20000,
      "avg7d": 18016,
      "mean7d": 18739,
      "median7d": 19000,
      "sampleCountLast7d": 210,
      "cleanSampleCount7d": 203,
      "outliersRemoved7d": 7,
      "min7d": 12000,
      "max7d": 25000,
      "totalUnits7d": 4902
    }
  }
}